{
  "welcomeMessageCollectionNamePage": "Fråga mig vad som helst om {{collectionName}} kollektionen",
  "others": {
    "popUpMessages": {
      "COLLECTION": "Letar du efter något speciellt i den här samlingen? Jag vet var du kan hitta det.",
      "DEFAULT": "Hej! Letar du efter något speciellt? Jag är här för att erbjuda dig en personlig shoppingupplevelse.",
      "PRODUCT": "Vill du veta mer om den här produkten? Jag har alla detaljer du behöver.",
      "SEARCH": "Hittar du inte vad du letar efter? Låt mig hjälpa dig att hitta exakt det du söker."
    },
    "suggestedReplies": {
      "COLLECTION": ["Vilka är dina bästsäljande produkter?", "Vad skiljer dina produkter från andra?", "Var är min beställning?"],
      "OTHER": ["Vilka är dina bästsäljande produkter?", "Vad skiljer dina produkter från andra?", "Var är min beställning?"],
      "PRODUCT": ["Vad utmärker den här produkten?", "Visa mig fler produkter som denna", "Vad är returpolicyn för den här produkten?"],
      "SEARCH": ["Visa de mest relevanta produkterna för mig", "Förfina resultaten baserat på mina krav", "Vilka är några populära val bland dessa?"]
    }
  },
  "translations": {
    "AMA": "Fråga mig vad som helst",
    "AskYourQuestion": "Ställ din fråga",
    "addCommentsHere": "Lägg till kommentarer här",
    "addToCart": "Lägg i kundvagn",
    "additionalDetails": "Ytterligare detaljer",
    "addtionalComments": "Ytterligare kommentarer",
    "askAboutProduct": "Fråga mer om denna produkt",
    "askAboutSpecificProduct": "Fråga om specifik produkt",
    "askAboutThis": "Fråga om detta",
    "askMeAnything": "Fråga mig vad som helst",
    "ask": "Fråga",
    "askMoreAboutThisProduct": "Fråga mer om denna produkt",
    "availOngoingSpecialOffer": "Jag vill utnyttja det pågående specialerbjudandet",
    "cartWaiting": "Låt inte varorna i kundvagnen vänta, handla nu!",
    "chatWithUS": "Chatta med oss 👋🏻",
    "checkOutThese": "Kolla in dessa val istället",
    "checkout": "Till kassan",
    "chooseYourCountry": "Välj ditt land",
    "directRewardNextPurchaseCoupon": "Tack för att du handlar hos oss! Vi har ett specialerbjudande på {{couponTitle}}. Vill du använda detta erbjudande vid ditt nästa köp?",
    "discountCouponTextBIC": "Hej där! Kul att se dig. 😃 Vi erbjuder en specialaffär: {{couponTitle}}. Redo att göra anspråk på din rabatt?",
    "discountCouponText": "Woohoo 🎉 Du är berättigad till {{couponTitle}}.",
    "getOffer": "Få erbjudande",
    "enter_email_here": "Ange din e-post här",
    "Email": "E-post",
    "searchCountryOrCode": "Sök land eller kod",
    "continueButtonText": "Fortsätt",
    "pleaseShareYourContactDetails": "Dela dina kontaktuppgifter",
    "quizSubText": "För att se rekommendationer baserade på dina preferenser.",
    "discountSubText": "För att få ditt erbjudande.",
    "conversationSubText": "För att fortsätta detta samtal.",
    "enter_phone_here": "Ange telefonnummer",
    "enterYourMessage": "Skriv ditt meddelande ...",
    "faqFull": "Vanliga frågor",
    "goToCart": "Gå till kundvagn",
    "hallucinationResponse": "Hallucination i svar",
    "handpicked": "Handplockade",
    "headerGreeting": "Hej, jag är",
    "iHaveAQuestion": "Jag har en fråga",
    "inaccurateInfo": "Felaktig information",
    "incorrectRecommendations": "Felaktiga rekommendationer",
    "insideCustomWorkflow": "Du är inne i {{query}}-flödet",
    "issueOptions": "Vilket alternativ beskriver bäst problemet?",
    "itWasOkay": "Det var okej",
    "leaveCustomWorkflow": "Du är på väg att lämna {{query}} flödet",
    "moreVariantsAvailable": "Fler varianter tillgängliga",
    "navigationPageTitle": "Du har kommit till {{navigationContext}} sidan",
    "needHelpAskAi": "Behöver hjälp? Fråga AI vad som helst!",
    "noSearchResultFound": "Inga resultat hittades",
    "noThanks": "Nej tack",
    "notHelpful": "Inte hjälpsam",
    "orderFormDontRememberLink": "Kommer du inte ihåg någon av dem?",
    "orderFormSubmitButton": "Skicka",
    "orderFormTrackingPortalLink": "Kolla vår spårningsportal",
    "orderFormUnverifiedInputPlaceholder": "E-postadress / Telefonnummer / Beställnings-ID",
    "orderFormUnverifiedOrderDetailsLabel": "Beställningsdetaljer",
    "orderFormUnverifiedTooltipText": "Du kan ange din e-post, telefonnummer eller ett beställnings-ID som börjar med '#'.",
    "orderFormUnverifiedTrackOrderPrompt": "Låt oss spåra din beställning",
    "orderFormVerifyTrackOrderPrompt": "Låt oss spåra din beställning",
    "orderFormVerifyOrderIdLabel": "Beställnings-ID",
    "orderFormVerifyOrderIdPlaceholder": "Beställnings-ID",
    "orderFormVerifyIdentityLabel": "Telefonnummer eller e-post",
    "orderFormVerifyIdentityPlaceholder": "Ange ditt telefonnummer eller e-post-ID",
    "orderFormVerifyOrderIdRequired": "Ange ett beställnings-ID.",
    "orderFormVerifyIdentityRequired": "Ange ditt telefonnummer eller e-post.",
    "orderFormVerifyIdentityInvalid": "Ange en giltig e-postadress eller telefonnummer.",
    "orderFormVerifyNoOrderFound": "Ingen beställning hittades med detta ID. Försök igen.",
    "orderFormVerifyEmailNotMatch": "Denna e-postadress matchar inte beställnings-ID:t. Försök igen.",
    "orderFormVerifyPhoneNotMatch": "Detta telefonnummer matchar inte beställnings-ID:t. Försök igen.",
    "orderFormEmailOnlyTrackOrderPrompt": "Ange din e-postadress för att spåra din beställning",
    "orderFormEmailOnlyOtpSentPrompt": "Vi har skickat en engångskod till din e-post. Ange den för att fortsätta",
    "orderFormEmailOnlyEmailLabel": "Ange e-postadress",
    "orderFormEmailOnlyEmailPlaceholder": "Ange din e-post",
    "orderFormEmailOnlyNoOrdersFound": "Inga beställningar hittades för denna e-post. Försök igen",
    "orderFormEnterOrderId": "Ange beställnings-ID",
    "orderFormEnterEmailOrPhone": "Ange e-post eller telefonnummer",
    "orderFormOrderIdPlaceholder": "123456",
    "orderFormEmailPhonePlaceholder": "alex@email.com or +91 9876543210",
    "orderFormTrackUsingEmailPhone": "Spåra med e-post/telefon",
    "orderFormTrackUsingOrderId": "Spåra med beställnings-ID",
    "orderFormForgotOrderId": "Glömt beställnings-ID?",
    "orderFormForgotEmailPhone": "Glömt e-post/telefon?",
    "orderFormValidOrderIdRequired": "Ange ett giltigt beställnings-ID.",
    "orderFormValidEmailPhoneRequired": "Ange en giltig e-postadress eller telefonnummer.",
    "orderFormNoOrdersFoundEmail": "Inga beställningar hittades för denna e-post. Försök igen",
    "orderFormNoAccountFoundEmail": "Inget konto hittades för denna e-post. Försök igen",
    "orderFormNoOrdersFoundPhone": "Inga beställningar hittades för detta nummer. Försök igen",
    "orderFormNoOrdersFoundOrderId": "Inga beställningar hittades för detta beställnings-ID. Försök igen",
    "orderFormEmailOnlyOtpLabel": "Ange verifieringskod",
    "orderFormEmailOnlyOtpPlaceholder": "Engångslösenord",
    "orderFormEmailOnlyOtpExpired": "Engångskoden har löpt ut. Försök igen.",
    "orderFormEmailOnlyOtpError": "Engångskoden stämmer inte. Försök igen.",
    "orderFormEmailOnlyResend": "Skicka igen",
    "orderFormEmailOnlyVerifyButton": "Verifiera",
    "orderFormEmailOnlyDontRememberEmail": "Glömt e-postadress?",
    "orderFormEmailOnlyResendIn": "Skicka igen om {{countdown}}s",
    "ourTopPicks": "Våra toppval",
    "ourTopProduct": "Våra topprodukter",
    "outOfStock": "Slut i lager",
    "poweredBy": "Drivs av",
    "quickActions": "Snabbåtgärder",
    "rewardForYou": "Belöningar bara för dig 🎉",
    "search": "Sök",
    "selectCountryCode": "Välj landskod",
    "searchQuery": "Fråga mig vad som helst om {{query}}",
    "seeCuratedRecommendations": "Se kurerade rekommendationer",
    "seeOurBestSellers": "Se våra bästsäljare",
    "similarTo": "Liknande som",
    "soldOut": "Slutsåld",
    "spinTheWheel": "snurra hjulet",
    "spinTheWheelExcitingRewards": "Snurra hjulet för att vinna spännande belöningar",
    "submit": "Skicka",
    "tapOnTo": "Tryck på för att",
    "tapToAsk": "Tryck för att ställa en fråga",
    "textLimit": "Maximal textgräns är {{MAX_LIMIT}} tecken",
    "thanksForTheFeedback": "Tack för din feedback.",
    "tryYourLuck": "Pröva lyckan",
    "unableToUnderstandQuestion": "Kan inte förstå frågan",
    "validEmailAddress": "Ange en giltig e-postadress",
    "validPhoneNumber": "Ange ett giltigt telefonnummer",
    "veryHelpful": "Mycket hjälpsam",
    "viewProduct": "Visa produkt",
    "viewResultsFromCollection": "Visa resultat från denna samling",
    "viewSimilarProducts": "Visa liknande produkter",
    "viewSimilar": "Visa liknande",
    "welcomeMessageCollectionPage": "Fråga mig vad som helst om vår {{collectionName}} samling!",
    "welcomeMessageCollectionPageGeneric": "Fråga mig vad som helst om våra produkter!",
    "welcomeMessageHomePage": "Välkommen till {{storeName}}! Hur kan jag hjälpa dig idag?",
    "welcomeMessageProductPage": "Fråga mig om vad som helst angående den här produkten",
    "whatAreYourBestSellers": "Vad är dina bästsäljande produkter?",
    "summarizeReviews": "Sammanfatta recensioner för den här produkten",
    "yesSure": "Ja, självklart!",
    "thinking": "Tänker",
    "findingYourAnswer": "Hittar ditt svar",
    "typingYourResponse": "Skriver ditt svar",
    "orderFormFallbackNoOtherOptions": "Inga problem, vi har andra alternativ tillgängliga för att hjälpa dig med din beställning.",
    "orderFormFallbackTalkToAgent": "Prata med en agent",
    "orderFormFallbackCheckTrackingPortal": "Kolla vår spårningsportal",
    "insideOrderTrackingFlow": "Du är inne i beställningsspårningsflödet",
    "startNewConversation": "Starta ny konversation",
    "orderItemsHeader": "Här är dina senaste 5 beställningar",
    "orderItemsSubtitle": "Välj den som du vill se detaljer för",
    "orderDetailsHeader": "Här är dina beställningsdetaljer",
    "clickHereToTrack": "Klicka här för att spåra",
    "usingTrackingNumber": "med numret [{{trackingNumber}}]",
    "orderTrackingComplete": "Din beställningsspårningsuppgift är klar",
    "orderFormNoOrderFoundForType": "Ingen beställning hittades för denna {{inputTypeLabel}}. Försök igen.",
    "orderFormInputTypeEmail": "E-postadress",
    "orderFormInputTypePhone": "Telefonnummer",
    "orderFormInputTypeOrderId": "Beställnings-ID",
    "bannerExitText": "Avsluta",
    "bannerProceedText": "Fortsätt?",
    "shippingPolicyIntent": "Vilken är er fraktpolicy",
    "contactDetailsIntent": "Hur kan jag kontakta er butik",
    "storeLocationIntent": "Var ligger era butiker",
    "subscriptionEnquiryIntent": "Jag vill veta mer om prenumeration",
    "orderTrackingIntent": "Jag vill spåra min order",
    "orderCancellationIntent": "Jag vill avboka min order",
    "returnsRefundsPolicyIntent": "Jag vill veta mer om retur- och återbetalningspolicy",
    "offersRewardsIntent": "Jag vill veta mer om aktuella erbjudanden eller belöningar",
    "offersEnquiryIntent": "Jag vill veta mer om min beställning",
    "shipping_policy": "Fraktpolicy",
    "contact_details": "Kontaktuppgifter",
    "store_location": "Butiksplats",
    "subscription_enquiry": "Prenumerationsförfrågan",
    "order_tracking": "Orderspårning",
    "order_cancellation": "Orderavbokning",
    "returns_refunds_policy": "Retur- och återbetalningspolicy",
    "offers_rewards": "Erbjudanden och belöningar",
    "orderListShowMore": "Visa mer",
    "orderListScrollToTop": "Scrolla till toppen",
    "orderListNeedHelp": "Behöver du hjälp?",
    "orderListCancelOrder": "Avbryt beställning",
    "orderListReturnOrder": "Returnera beställning",
    "orderListCancelOrderMessage": "Mitt beställnings-ID är {{orderId}}. Jag vill avbryta min beställning.",
    "orderListReturnOrderMessage": "Mitt beställnings-ID är {{orderId}}. Jag vill returnera min beställning.",
    "orderListNeedHelpMessage": "Jag spårade min beställning. Jag har fler frågor om min beställning {{orderId}}",
    "returnToChat": "Återgå till chatten",
    "orderFormOtpTitle": "Vi har skickat en 6-siffrig kod till din e-post.",
    "orderFormEmailOnlyDidntReceiveCode": "Fick du inte koden?",
    "orderFormVerifyNoOrderFoundPhone": "Inga beställningar hittades för detta nummer. Försök igen.",
    "orderFormForgotEverything": "Forgot everything?",
    "orderFormEmailOnlyResendNow": "Skicka om nu",
    "orderFormVerifyNoOrderFoundEmail": "Inga beställningar hittades för denna e-post. Försök igen.",
    "orderOtpRateLimitError": "Du har överskridit det maximala antalet OTP-förfrågningar. Försök igen om en timme.",
    "seeOtherPicks": "Se våra andra toppval",
    "orderFormVerifyNoOrderFoundOrderId": "Inga beställningar hittades för detta beställnings-ID. Försök igen.",
    "orderFormEmailOnlyTitle": "Låt oss spåra din beställning",
    "orderListHereAreYourOrders": "Här är dina beställningar",
    "orderFormBackButton": "Tillbaka",
    "orderFormPhoneNumberLabel": "Ange telefonnummer",
    "orderFormPincodeLabel": "Ange postnummer",
    "orderFormPincodePlaceholder": "Postnummer",
    "orderFormPhoneNumberError": "Vänligen ange ett telefonnummer",
    "orderFormPincodeError": "Vänligen ange ett postnummer",
    "orderFormNoOrdersFoundPhoneAndPincode": "Inga beställningar hittades med det här telefonnumret och postnumret",
    "orderFormForgotDetails": "Glömt dina detaljer?",
    "recommendLike": "Rekommendera liknande",
    "productSpecialistInputPlaceholder": "Skriv din fråga här",
    "continueButton": "Klicka här för att fortsätta",
    "olderConversations": "Äldre konversationer"
  }
}
